crowdstrike_aidr_google_genai/__init__.py
crowdstrike_aidr_google_genai/client.py
crowdstrike_aidr_google_genai/errors.py
crowdstrike_aidr_google_genai/models.py
crowdstrike_aidr_google_genai/py.typed
crowdstrike_aidr_google_genai-0.1.1.dist-info/WHEEL
crowdstrike_aidr_google_genai-0.1.1.dist-info/METADATA
crowdstrike_aidr_google_genai-0.1.1.dist-info/RECORD
