Metadata-Version: 2.4
Name: crowdstrike-aidr-google-genai
Version: 0.1.1
Summary: A wrapper around the Google GenAI Python SDK
Author: CrowdStrike
Author-email: CrowdStrike <support@crowdstrike.com>
License-Expression: MIT
Requires-Dist: crowdstrike-aidr~=0.4.2
Requires-Dist: google-genai~=1.54.0
Requires-Dist: typing-extensions~=4.15.0
Requires-Python: >=3.12
